CCC_DoU.py
CCC_DoU-0.0.1.dist-info/LICENSE.txt
CCC_DoU-0.0.1.dist-info/METADATA
CCC_DoU-0.0.1.dist-info/WHEEL
CCC_DoU-0.0.1.dist-info/top_level.txt
CCC_DoU-0.0.1.dist-info/RECORD
