Metadata-Version: 2.1
Name: CCC-DoU
Version: 0.0.1
Summary: Chatterjee Correlation coefficient calculator with p-value
Home-page: https://github.com/Partha0312bio/CCC_DU
Author: Shubhabrata Dokal
License: UNKNOWN
Keywords: Chatterjee Correlation Coefficient,non linear correlation calculation ,
Platform: UNKNOWN
Classifier: Programming Language :: Python :: 3
Classifier: License :: OSI Approved :: MIT License
Classifier: Operating System :: OS Independent
Requires-Python: >=3.6
License-File: LICENSE.txt
Requires-Dist: numpy
Requires-Dist: pandas
